flask_dance_google_auth/__init__.py
Flask_Dance_Google_Auth-0.0.6.dist-info/LICENSE
Flask_Dance_Google_Auth-0.0.6.dist-info/METADATA
Flask_Dance_Google_Auth-0.0.6.dist-info/WHEEL
Flask_Dance_Google_Auth-0.0.6.dist-info/top_level.txt
Flask_Dance_Google_Auth-0.0.6.dist-info/RECORD
